qdarkstyle/__init__.py
qdarkstyle/__main__.py
qdarkstyle/colorsystem.py
qdarkstyle/palette.py
qdarkstyle/dark/__init__.py
qdarkstyle/dark/_variables.scss
qdarkstyle/dark/darkstyle.qrc
qdarkstyle/dark/darkstyle.qss
qdarkstyle/dark/darkstyle_rc.py
qdarkstyle/dark/main.scss
qdarkstyle/dark/palette.py
qdarkstyle/dark/rc/arrow_down.png
qdarkstyle/dark/rc/arrow_down@2x.png
qdarkstyle/dark/rc/arrow_down_disabled.png
qdarkstyle/dark/rc/arrow_down_disabled@2x.png
qdarkstyle/dark/rc/arrow_down_focus.png
qdarkstyle/dark/rc/arrow_down_focus@2x.png
qdarkstyle/dark/rc/arrow_down_pressed.png
qdarkstyle/dark/rc/arrow_down_pressed@2x.png
qdarkstyle/dark/rc/arrow_left.png
qdarkstyle/dark/rc/arrow_left@2x.png
qdarkstyle/dark/rc/arrow_left_disabled.png
qdarkstyle/dark/rc/arrow_left_disabled@2x.png
qdarkstyle/dark/rc/arrow_left_focus.png
qdarkstyle/dark/rc/arrow_left_focus@2x.png
qdarkstyle/dark/rc/arrow_left_pressed.png
qdarkstyle/dark/rc/arrow_left_pressed@2x.png
qdarkstyle/dark/rc/arrow_right.png
qdarkstyle/dark/rc/arrow_right@2x.png
qdarkstyle/dark/rc/arrow_right_disabled.png
qdarkstyle/dark/rc/arrow_right_disabled@2x.png
qdarkstyle/dark/rc/arrow_right_focus.png
qdarkstyle/dark/rc/arrow_right_focus@2x.png
qdarkstyle/dark/rc/arrow_right_pressed.png
qdarkstyle/dark/rc/arrow_right_pressed@2x.png
qdarkstyle/dark/rc/arrow_up.png
qdarkstyle/dark/rc/arrow_up@2x.png
qdarkstyle/dark/rc/arrow_up_disabled.png
qdarkstyle/dark/rc/arrow_up_disabled@2x.png
qdarkstyle/dark/rc/arrow_up_focus.png
qdarkstyle/dark/rc/arrow_up_focus@2x.png
qdarkstyle/dark/rc/arrow_up_pressed.png
qdarkstyle/dark/rc/arrow_up_pressed@2x.png
qdarkstyle/dark/rc/base_icon.png
qdarkstyle/dark/rc/base_icon@2x.png
qdarkstyle/dark/rc/base_icon_disabled.png
qdarkstyle/dark/rc/base_icon_disabled@2x.png
qdarkstyle/dark/rc/base_icon_focus.png
qdarkstyle/dark/rc/base_icon_focus@2x.png
qdarkstyle/dark/rc/base_icon_pressed.png
qdarkstyle/dark/rc/base_icon_pressed@2x.png
qdarkstyle/dark/rc/branch_closed.png
QDarkStyle-3.2.3.dist-info/AUTHORS.rst
QDarkStyle-3.2.3.dist-info/LICENSE.rst
QDarkStyle-3.2.3.dist-info/METADATA
QDarkStyle-3.2.3.dist-info/WHEEL
QDarkStyle-3.2.3.dist-info/entry_points.txt
QDarkStyle-3.2.3.dist-info/top_level.txt
QDarkStyle-3.2.3.dist-info/RECORD
