Metadata-Version: 2.1
Name: QDarkStyle
Version: 3.2.3
Summary: The most complete dark/light style sheet for C++/Python and Qt applications
Home-page: https://github.com/ColinDuquesnoy/QDarkStyleSheet
Author: Colin Duquesnoy
Author-email: colin.duquesnoy@gmail.com
License: MIT
Project-URL: Issues, https://github.com/ColinDuquesnoy/QDarkStyleSheet/issues
Project-URL: Docs, https://qdarkstylesheet.readthedocs.io/en/stable
Classifier: Development Status :: 5 - Production/Stable
Classifier: Environment :: X11 Applications :: Qt
Classifier: Environment :: Win32 (MS Windows)
Classifier: Intended Audience :: Developers
Classifier: License :: OSI Approved :: MIT License
Classifier: Operating System :: Microsoft :: Windows
Classifier: Operating System :: POSIX :: Linux
Classifier: Operating System :: MacOS
Classifier: Programming Language :: Python :: 3
Classifier: Programming Language :: Python :: 3.6
Classifier: Programming Language :: Python :: 3.7
Classifier: Programming Language :: Python :: 3.8
Classifier: Programming Language :: Python :: 3.9
Classifier: Programming Language :: Python :: 3.10
Classifier: Topic :: Software Development :: Libraries :: Application Frameworks
License-File: LICENSE.rst
License-File: AUTHORS.rst
Requires-Dist: qtpy>=2
Provides-Extra: develop
Requires-Dist: qtsass; extra == "develop"
Requires-Dist: watchdog; extra == "develop"
Provides-Extra: docs
Requires-Dist: sphinx; extra == "docs"
Requires-Dist: sphinx_rtd_theme; extra == "docs"
Provides-Extra: example
Requires-Dist: pyqt5; extra == "example"
Requires-Dist: pyside2; extra == "example"
